logcat_parser/__init__.py
logcat_parser-0.2.4.dist-info/DESCRIPTION.rst
logcat_parser-0.2.4.dist-info/METADATA
logcat_parser-0.2.4.dist-info/RECORD
logcat_parser-0.2.4.dist-info/WHEEL
logcat_parser-0.2.4.dist-info/metadata.json
logcat_parser-0.2.4.dist-info/top_level.txt
