Metadata-Version: 2.0
Name: logcat-parser
Version: 0.2.4
Summary: A parser for Android logcat in binary format.
Home-page: https://github.com/aheadlead/logcat-parser
Author: weiyulan
Author-email: yulan.wyl@gmail.com
License: GPL
Keywords: adb,logcat,android,logging
Platform: UNKNOWN
Classifier: Development Status :: 2 - Pre-Alpha
Classifier: Environment :: Console
Classifier: Intended Audience :: Developers
Classifier: License :: OSI Approved :: GNU General Public License v3 (GPLv3)
Classifier: Operating System :: POSIX :: Linux
Classifier: Programming Language :: Python :: 3.4
Classifier: Programming Language :: Python :: 3.6
Classifier: Topic :: Software Development :: Testing
